scrapyu/__init__.py
scrapyu/_cookies.py
scrapyu/_markdown.py
scrapyu/_mongodb.py
scrapyu/_redis.py
scrapyu/_useragent.py
scrapyu/cmdline.py
scrapyu/settings.py
scrapyu/templates/spiders/single.tmpl
scrapyu/templates/spiders/single_splash.tmpl
scrapyu/utils.py
scrapyu-0.1.12.dist-info/entry_points.txt
scrapyu-0.1.12.dist-info/LICENSE
scrapyu-0.1.12.dist-info/WHEEL
scrapyu-0.1.12.dist-info/METADATA
scrapyu-0.1.12.dist-info/RECORD
