Metadata-Version: 2.1
Name: scrapyu
Version: 0.1.12
Summary: Scrapy utils
Home-page: https://github.com/lin-zone/scrapyu
Keywords: scrapy,pipelines,middlewares,utils,dupefilter
Author: lin-zone
Author-email: z_one10@163.com
Requires-Python: >=3.6,<4.0
Classifier: Framework :: Scrapy
Classifier: Intended Audience :: Developers
Classifier: License :: OSI Approved :: MIT License
Classifier: Natural Language :: Chinese (Simplified)
Classifier: Programming Language :: Python :: 3
Classifier: Programming Language :: Python :: 3.6
Classifier: Programming Language :: Python :: 3.7
Classifier: Programming Language :: Python :: 3.8
Classifier: Topic :: Internet :: WWW/HTTP
Classifier: Topic :: Utilities
Requires-Dist: fake-useragent (==0.1.11)
Requires-Dist: html2text (==2019.9.26)
Requires-Dist: path-py (==12.4.0)
Requires-Dist: pymongo (==3.10.0)
Requires-Dist: pytest-cov (>=2.8,<3.0)
Requires-Dist: redis (==3.3.11)
Requires-Dist: scrapy (>=1.8,<2.0)
Requires-Dist: selenium (==3.141.0)
Requires-Dist: testfixtures (==6.10.3)
Project-URL: Repository, https://github.com/lin-zone/scrapyu
